AUTHORS.rst
CONTRIBUTING.rst
HISTORY.rst
LICENSE
MANIFEST.in
README.rst
setup.cfg
setup.py
calorimeter/__init__.py
calorimeter/plot.py
calorimeter/scan.py
calorimeter/tools.py
calorimeter.egg-info/PKG-INFO
calorimeter.egg-info/SOURCES.txt
calorimeter.egg-info/dependency_links.txt
calorimeter.egg-info/entry_points.txt
calorimeter.egg-info/not-zip-safe
calorimeter.egg-info/requires.txt
calorimeter.egg-info/top_level.txt
docs/Makefile
docs/authors.rst
docs/calorimeter.rst
docs/conf.py
docs/contributing.rst
docs/history.rst
docs/index.rst
docs/installation.rst
docs/make.bat
docs/modules.rst
docs/readme.rst
docs/usage.rst
docs/_build/html/_static/file.png
docs/_build/html/_static/minus.png
docs/_build/html/_static/plus.png
tests/__init__.py
tests/test_plot.py
tests/test_scan.py
tests/test_tools.py
tests/files/6HAW158-2.csv
tests/files/6HAW158.csv
tests/files/7HAW008-2.csv
tests/files/7HAW008.csv
tests/files/7HAW010-2.csv
tests/files/7HAW010.csv
tests/files/7HAW012-2.csv
tests/files/7HAW012.csv
tests/files/7HAW104.csv